cmpipe/FilterStage.py
cmpipe/FilterWorker.py
cmpipe/OrderedStage.py
cmpipe/OrderedWorker.py
cmpipe/Pipeline.py
cmpipe/Stage.py
cmpipe/TubeP.py
cmpipe/TubeQ.py
cmpipe/UnorderedStage.py
cmpipe/UnorderedWorker.py
cmpipe/__init__.py
cmpipe-1.0.8.dist-info/LICENSE
cmpipe-1.0.8.dist-info/METADATA
cmpipe-1.0.8.dist-info/WHEEL
cmpipe-1.0.8.dist-info/top_level.txt
cmpipe-1.0.8.dist-info/RECORD
