Metadata-Version: 2.1
Name: cmpipe
Version: 1.0.8
Summary: Multiprocess pipeline toolkit
Home-page: http://vmlaker.github.io/cmpipe
Author: Velimir Mlaker
Author-email: velimir.mlaker@gmail.com
License: MIT
Classifier: Development Status :: 5 - Production/Stable
Classifier: Intended Audience :: Developers
Classifier: License :: Freeware
Classifier: Operating System :: OS Independent
Classifier: Programming Language :: Python
Classifier: Programming Language :: Python :: 3
Classifier: Topic :: Software Development :: Libraries :: Application Frameworks
Classifier: Topic :: Software Development :: Libraries :: Python Modules
License-File: LICENSE
